tap_s3_csv/__init__.py
tap_s3_csv/config.py
tap_s3_csv/conversion.py
tap_s3_csv/discover.py
tap_s3_csv/s3.py
tap_s3_csv/sync.py
tap_s3_csv_kasparg-1.0.0.dist-info/LICENSE
tap_s3_csv_kasparg-1.0.0.dist-info/METADATA
tap_s3_csv_kasparg-1.0.0.dist-info/WHEEL
tap_s3_csv_kasparg-1.0.0.dist-info/entry_points.txt
tap_s3_csv_kasparg-1.0.0.dist-info/top_level.txt
tap_s3_csv_kasparg-1.0.0.dist-info/RECORD
