Metadata-Version: 2.1
Name: tap-s3-csv-kasparg
Version: 1.0.0
Summary: Singer.io tap for extracting CSV files from S3
Home-page: https://singer.io
Author: Stitch
License: UNKNOWN
Platform: UNKNOWN
Classifier: Programming Language :: Python :: 3 :: Only
Requires-Dist: backoff (==1.3.2)
Requires-Dist: boto3 (==1.9.57)
Requires-Dist: singer-encodings (==0.0.3)
Requires-Dist: singer-python (==5.1.5)
Requires-Dist: voluptuous (==0.10.5)
Provides-Extra: dev
Requires-Dist: ipdb (==0.11) ; extra == 'dev'
